MANIFEST.in
Makefile
README
setup.cfg
setup.py
test/__init__.py
test/__init__.pyc
test/test_compile.py
test/test_stress.py
test/test_web.py
test/test_web_304.py
test/__pycache__/test_compile.cpython-27-PYTEST.pyc
test/__pycache__/test_stress.cpython-27-PYTEST.pyc
test/__pycache__/test_web.cpython-27-PYTEST.pyc
test/__pycache__/test_web_304.cpython-27-PYTEST.pyc
tiddlywebplugins/__init__.py
tiddlywebplugins/etagcache.py
tiddlywebplugins.etagcache.egg-info/PKG-INFO
tiddlywebplugins.etagcache.egg-info/SOURCES.txt
tiddlywebplugins.etagcache.egg-info/dependency_links.txt
tiddlywebplugins.etagcache.egg-info/namespace_packages.txt
tiddlywebplugins.etagcache.egg-info/not-zip-safe
tiddlywebplugins.etagcache.egg-info/requires.txt
tiddlywebplugins.etagcache.egg-info/top_level.txt