Metadata-Version: 1.0
Name: tiddlywebplugins.etagcache
Version: 0.10.0
Summary: Cache TiddlyWeb ETags so that a 304 can be sent without checking store
Home-page: http://pypi.python.org/pypi/tiddlywebplugins.etagcache
Author: Chris Dent
Author-email: cdent@peermore.com
License: UNKNOWN
Platform: Posix; MacOS X; Windows
